delete/__init__.py
delete/logging.py
delete_cli-2.0.0.dist-info/LICENSE
delete_cli-2.0.0.dist-info/METADATA
delete_cli-2.0.0.dist-info/WHEEL
delete_cli-2.0.0.dist-info/entry_points.txt
delete_cli-2.0.0.dist-info/RECORD
