Metadata-Version: 2.1
Name: delete-cli
Version: 2.0.0
Summary: A simple, cross-platform, command-line move-to-trash.
Home-page: https://delete-cli.readthedocs.io
License: MIT
Keywords: command-line,utility
Author: Geoffrey Lentner
Author-email: glentner@purdue.edu
Requires-Python: >=3.12,<4.0
Classifier: Development Status :: 5 - Production/Stable
Classifier: License :: OSI Approved :: MIT License
Classifier: Operating System :: MacOS
Classifier: Operating System :: Microsoft :: Windows
Classifier: Operating System :: POSIX :: Linux
Classifier: Programming Language :: Python :: 3
Classifier: Programming Language :: Python :: 3.12
Classifier: Programming Language :: Python :: 3.13
Requires-Dist: cmdkit (==2.7.4)
Project-URL: Documentation, https://delete-cli.readthedocs.io
Project-URL: Repository, https://github.com/glentner/delete-cli
